{
    "chain": [
        {
            "index": 0,
            "transactions": [],
            "timestamp": 1775537361.022352,
            "previous_hash": "0",
            "nonce": 0,
            "hash": "23f2477708640683007cf2f50c8454638ad484aa12ee1d1e5d64bc28755145fc"
        },
        {
            "index": 1,
            "transactions": [
                {
                    "user": "node",
                    "ev_model": "Tesla Model 3",
                    "time": 30,
                    "amount": 15.0,
                    "transaction_id": 1,
                    "timestamp": 1775540298.0657861,
                    "previous_hash": "23f2477708640683007cf2f50c8454638ad484aa12ee1d1e5d64bc28755145fc"
                }
            ],
            "timestamp": 1775540298.0658014,
            "previous_hash": "23f2477708640683007cf2f50c8454638ad484aa12ee1d1e5d64bc28755145fc",
            "nonce": 973,
            "hash": "006570a6626ffa04ca75ee8df073866587a717ae3e4ae029765f9cea310443d7"
        },
        {
            "index": 2,
            "transactions": [
                {
                    "user": "node",
                    "ev_model": "Tesla Model 3",
                    "time": 30,
                    "amount": 15.0,
                    "transaction_id": 2,
                    "timestamp": 1775540471.1344056,
                    "previous_hash": "006570a6626ffa04ca75ee8df073866587a717ae3e4ae029765f9cea310443d7"
                }
            ],
            "timestamp": 1775540471.1344197,
            "previous_hash": "006570a6626ffa04ca75ee8df073866587a717ae3e4ae029765f9cea310443d7",
            "nonce": 335,
            "hash": "003c4b70e1343af924d765eb8057ad9ce5c9a711e11802673418cd724ca59b6d"
        },
        {
            "index": 3,
            "transactions": [
                {
                    "user": "node",
                    "ev_model": "Tesla Model 3",
                    "time": 30,
                    "amount": 15.0,
                    "transaction_id": 3,
                    "timestamp": 1775542024.2622154,
                    "previous_hash": "003c4b70e1343af924d765eb8057ad9ce5c9a711e11802673418cd724ca59b6d"
                }
            ],
            "timestamp": 1775542024.262225,
            "previous_hash": "003c4b70e1343af924d765eb8057ad9ce5c9a711e11802673418cd724ca59b6d",
            "nonce": 168,
            "hash": "006658b3528953517f8a2e1be14fd92d4ab4b2342febb98111145bc4866f2ba2"
        },
        {
            "index": 4,
            "transactions": [
                {
                    "user": "node",
                    "ev_model": "Tesla Model 3",
                    "time": 30,
                    "amount": 15.0,
                    "transaction_id": 4,
                    "timestamp": 1775542262.8341386,
                    "previous_hash": "006658b3528953517f8a2e1be14fd92d4ab4b2342febb98111145bc4866f2ba2"
                }
            ],
            "timestamp": 1775542262.834152,
            "previous_hash": "006658b3528953517f8a2e1be14fd92d4ab4b2342febb98111145bc4866f2ba2",
            "nonce": 129,
            "hash": "00eaaed89d43e44c4818799172eba7b3826b07ee5ceb11f92daf3c831d52ddf1"
        },
        {
            "index": 5,
            "transactions": [
                {
                    "user": "node",
                    "ev_model": "Tesla Model 3",
                    "time": 30,
                    "amount": 15.0,
                    "transaction_id": 5,
                    "timestamp": 1775542482.3911808,
                    "previous_hash": "00eaaed89d43e44c4818799172eba7b3826b07ee5ceb11f92daf3c831d52ddf1"
                }
            ],
            "timestamp": 1775542482.3911848,
            "previous_hash": "00eaaed89d43e44c4818799172eba7b3826b07ee5ceb11f92daf3c831d52ddf1",
            "nonce": 37,
            "hash": "009eac2b1bb18a375ea61246e24cc1a3424f790cd50efc9d25bfd30e88c2fd04"
        },
        {
            "index": 6,
            "transactions": [
                {
                    "user": "node",
                    "ev_model": "RECHARGE_NODE",
                    "time": 0,
                    "amount": 100.0,
                    "transaction_id": "TOPUP_1775543746",
                    "timestamp": 1775543746.2271295,
                    "previous_hash": "009eac2b1bb18a375ea61246e24cc1a3424f790cd50efc9d25bfd30e88c2fd04"
                }
            ],
            "timestamp": 1775543746.2271352,
            "previous_hash": "009eac2b1bb18a375ea61246e24cc1a3424f790cd50efc9d25bfd30e88c2fd04",
            "nonce": 8,
            "hash": "00dbba9ed9dfc6cef36f5e684eb52612775b624a27d8e48254642de7599cdbfc"
        },
        {
            "index": 7,
            "transactions": [
                {
                    "user": "hello",
                    "ev_model": "RECHARGE_NODE",
                    "time": 0,
                    "amount": 100.0,
                    "transaction_id": "TOPUP_1775544081",
                    "timestamp": 1775544081.503518,
                    "previous_hash": "00dbba9ed9dfc6cef36f5e684eb52612775b624a27d8e48254642de7599cdbfc"
                }
            ],
            "timestamp": 1775544081.5035276,
            "previous_hash": "00dbba9ed9dfc6cef36f5e684eb52612775b624a27d8e48254642de7599cdbfc",
            "nonce": 361,
            "hash": "00c4c1fb892e3f1651931301b2ef4744593354b5b8377c32046abb6a2c39622e"
        },
        {
            "index": 8,
            "transactions": [
                {
                    "user": "hello",
                    "ev_model": "Kia EV6",
                    "time": 30,
                    "amount": 22.5,
                    "transaction_id": 6,
                    "timestamp": 1775544126.2433865,
                    "previous_hash": "00c4c1fb892e3f1651931301b2ef4744593354b5b8377c32046abb6a2c39622e"
                }
            ],
            "timestamp": 1775544126.2433956,
            "previous_hash": "00c4c1fb892e3f1651931301b2ef4744593354b5b8377c32046abb6a2c39622e",
            "nonce": 61,
            "hash": "0025584ee469220fe2ee79f38eec37b19cb3b5e865c874035c242c69a950e422"
        },
        {
            "index": 9,
            "transactions": [
                {
                    "user": "node",
                    "ev_model": "Tesla Model 3",
                    "time": 30,
                    "amount": 15.0,
                    "transaction_id": 9,
                    "timestamp": 1775545348.3396735,
                    "previous_hash": "0025584ee469220fe2ee79f38eec37b19cb3b5e865c874035c242c69a950e422"
                }
            ],
            "timestamp": 1775545348.339687,
            "previous_hash": "0025584ee469220fe2ee79f38eec37b19cb3b5e865c874035c242c69a950e422",
            "nonce": 22,
            "hash": "00a12da419cc80aabedc9aa1e1c1fcb068aa2be8c4588729bfbe1c0d8f8453fe"
        },
        {
            "index": 10,
            "transactions": [
                {
                    "user": "node",
                    "ev_model": "Tesla Model 3",
                    "time": 30,
                    "amount": 15.0,
                    "transaction_id": 10,
                    "timestamp": 1775545381.6850219,
                    "previous_hash": "00a12da419cc80aabedc9aa1e1c1fcb068aa2be8c4588729bfbe1c0d8f8453fe"
                }
            ],
            "timestamp": 1775545381.6850371,
            "previous_hash": "00a12da419cc80aabedc9aa1e1c1fcb068aa2be8c4588729bfbe1c0d8f8453fe",
            "nonce": 166,
            "hash": "0063e758f3d08780fcdc3f274241fa856775e34e8e4a6bd2befbdcf09faf38c0"
        },
        {
            "index": 11,
            "transactions": [
                {
                    "user": "node",
                    "ev_model": "Tesla Model 3",
                    "time": 30,
                    "amount": 15.0,
                    "transaction_id": 11,
                    "timestamp": 1775545756.465178,
                    "previous_hash": "0063e758f3d08780fcdc3f274241fa856775e34e8e4a6bd2befbdcf09faf38c0"
                }
            ],
            "timestamp": 1775545756.4651859,
            "previous_hash": "0063e758f3d08780fcdc3f274241fa856775e34e8e4a6bd2befbdcf09faf38c0",
            "nonce": 348,
            "hash": "00ad2833b159a1fb4a148eb8bd5d4ea63915403cc7baa48e45bd4a23452cc116"
        },
        {
            "index": 12,
            "transactions": [
                {
                    "user": "node",
                    "ev_model": "Tesla Model 3",
                    "time": 30,
                    "amount": 15.0,
                    "transaction_id": 12,
                    "timestamp": 1775545919.3405676,
                    "previous_hash": "00ad2833b159a1fb4a148eb8bd5d4ea63915403cc7baa48e45bd4a23452cc116"
                }
            ],
            "timestamp": 1775545919.340576,
            "previous_hash": "00ad2833b159a1fb4a148eb8bd5d4ea63915403cc7baa48e45bd4a23452cc116",
            "nonce": 302,
            "hash": "000184aee7ab50cc4e965eb7f52bfa5c9b91d0b2ff16b230a6afa611b85f0993"
        },
        {
            "index": 13,
            "transactions": [
                {
                    "user": "node",
                    "ev_model": "Tesla Model 3",
                    "time": 30,
                    "amount": 15.0,
                    "transaction_id": 13,
                    "timestamp": 1775546216.5871654,
                    "previous_hash": "000184aee7ab50cc4e965eb7f52bfa5c9b91d0b2ff16b230a6afa611b85f0993"
                }
            ],
            "timestamp": 1775546216.5871773,
            "previous_hash": "000184aee7ab50cc4e965eb7f52bfa5c9b91d0b2ff16b230a6afa611b85f0993",
            "nonce": 718,
            "hash": "000f010ee198e02be90ab99222d6f33392b109a28ab92877a3d2ca906cb8696e"
        },
        {
            "index": 14,
            "transactions": [
                {
                    "user": "node",
                    "ev_model": "Tesla Model 3",
                    "time": 60,
                    "amount": 30.0,
                    "transaction_id": 14,
                    "timestamp": 1775546551.5813262,
                    "previous_hash": "000f010ee198e02be90ab99222d6f33392b109a28ab92877a3d2ca906cb8696e"
                }
            ],
            "timestamp": 1775546551.581335,
            "previous_hash": "000f010ee198e02be90ab99222d6f33392b109a28ab92877a3d2ca906cb8696e",
            "nonce": 6,
            "hash": "004dda3a0baa8a9d657a30eef41762e8b6411ac5990d5b5d2c26ad77ecdbda26"
        },
        {
            "index": 15,
            "transactions": [
                {
                    "user": "node",
                    "ev_model": "Tesla Model 3",
                    "time": 30,
                    "amount": 15.0,
                    "transaction_id": 15,
                    "timestamp": 1775546764.13509,
                    "previous_hash": "004dda3a0baa8a9d657a30eef41762e8b6411ac5990d5b5d2c26ad77ecdbda26"
                }
            ],
            "timestamp": 1775546764.1351016,
            "previous_hash": "004dda3a0baa8a9d657a30eef41762e8b6411ac5990d5b5d2c26ad77ecdbda26",
            "nonce": 354,
            "hash": "0011fa23ec14c6cc8d6500f90cbab28bd9bd43b155d7aae9610923a4b71f8381"
        },
        {
            "index": 16,
            "transactions": [
                {
                    "user": "node",
                    "ev_model": "Tesla Model 3",
                    "time": 30,
                    "amount": 15.0,
                    "transaction_id": 16,
                    "timestamp": 1775547053.5262873,
                    "previous_hash": "0011fa23ec14c6cc8d6500f90cbab28bd9bd43b155d7aae9610923a4b71f8381"
                }
            ],
            "timestamp": 1775547053.5263011,
            "previous_hash": "0011fa23ec14c6cc8d6500f90cbab28bd9bd43b155d7aae9610923a4b71f8381",
            "nonce": 289,
            "hash": "00982344b5fa4bac26fe7624c6c1ef8ec94b8a0eaf82c501f3ca29a4d3f9821f"
        },
        {
            "index": 17,
            "transactions": [
                {
                    "user": "node",
                    "ev_model": "Tesla Model 3",
                    "time": 30,
                    "amount": 15.0,
                    "transaction_id": 18,
                    "timestamp": 1775548520.710164,
                    "previous_hash": "00982344b5fa4bac26fe7624c6c1ef8ec94b8a0eaf82c501f3ca29a4d3f9821f"
                }
            ],
            "timestamp": 1775548520.710177,
            "previous_hash": "00982344b5fa4bac26fe7624c6c1ef8ec94b8a0eaf82c501f3ca29a4d3f9821f",
            "nonce": 8,
            "hash": "0014d77bf6257a9af356a9d5d83475893260b64689c35db0193818368f0b64ea"
        }
    ],
    "unconfirmed": []
}